automail/__init__.py
automail/__main__.py
automail/cli.py
automail/core/__init__.py
automail/core/helpers.py
automail/core/parsers.py
automail/core/generators/__init__.py
automail/core/generators/_readme.py
automail/core/generators/_setup.py
nina-0.0.5.dist-info/LICENSE-autogen.md
nina-0.0.5.dist-info/LICENSE.md
nina-0.0.5.dist-info/METADATA
nina-0.0.5.dist-info/WHEEL
nina-0.0.5.dist-info/entry_points.txt
nina-0.0.5.dist-info/top_level.txt
nina-0.0.5.dist-info/RECORD
