Metadata-Version: 2.1
Name: nina
Version: 0.0.5
Summary: Generate README.md and setup.py quickly
Home-page: https://github.com/Ronald-TR/nina
Author: Ronald Rodrigues
Author-email: ronald-farias@outlook.com
License: UNKNOWN
Platform: UNKNOWN
Classifier: Programming Language :: Python :: 3
Classifier: License :: OSI Approved :: MIT License
Classifier: Operating System :: OS Independent
Requires-Dist: colorama (>=0.4.1)
Requires-Dist: PyInquirer (>=1.0.3)
Requires-Dist: pyfiglet (>=0.8.post1)
Requires-Dist: requests
